{"format": "torch", "nodes": [{"name": "conv1", "id": 46914385125216, "class_name": "Conv2d(3, 565, kernel_size=(5, 5), stride=(1, 1))", "parameters": [["weight", [565, 3, 5, 5]], ["bias", [565]]], "output_shape": [[4, 565, 28, 28]], "num_parameters": [42375, 565]}, {"name": "pool", "id": 46914251514712, "class_name": "MaxPool2d(kernel_size=2, stride=2, padding=0, dilation=1, ceil_mode=False)", "parameters": [], "output_shape": [[4, 565, 14, 14]], "num_parameters": []}, {"name": "conv2", "id": 46914243213968, "class_name": "Conv2d(565, 619, kernel_size=(7, 7), stride=(1, 1))", "parameters": [["weight", [619, 565, 7, 7]], ["bias", [619]]], "output_shape": [[4, 619, 8, 8]], "num_parameters": [17137015, 619]}, {"name": "fc1", "id": 46914243297576, "class_name": "Linear(in_features=9904, out_features=3926, bias=True)", "parameters": [["weight", [3926, 9904]], ["bias", [3926]]], "output_shape": [[4, 3926]], "num_parameters": [38883104, 3926]}, {"name": "fc2", "id": 46914243297800, "class_name": "Linear(in_features=3926, out_features=463, bias=True)", "parameters": [["weight", [463, 3926]], ["bias", [463]]], "output_shape": [[4, 463]], "num_parameters": [1817738, 463]}, {"name": "fc3", "id": 46912516359448, "class_name": "Linear(in_features=463, out_features=10, bias=True)", "parameters": [["weight", [10, 463]], ["bias", [10]]], "output_shape": [[4, 10]], "num_parameters": [4630, 10]}], "edges": []}